[
  {
    "id": "child-development",
    "name": "Child Development",
    "issn": ["0009-3920", "1467-8624"],
    "aliases": ["Child Dev"],
    "publisher": "SRCD / Wiley",
    "field": "developmental-psychology",
    "priority": "flagship"
  },
  {
    "id": "developmental-science",
    "name": "Developmental Science",
    "issn": ["1363-755X", "1467-7684"],
    "aliases": ["Dev Sci"],
    "publisher": "Wiley",
    "field": "developmental-cognitive-science",
    "priority": "flagship"
  },
  {
    "id": "developmental-psychology",
    "name": "Developmental Psychology",
    "issn": ["0012-1649", "1939-0599"],
    "aliases": ["Dev Psychol"],
    "publisher": "APA",
    "field": "developmental-psychology",
    "priority": "flagship"
  },
  {
    "id": "jecp",
    "name": "Journal of Experimental Child Psychology",
    "issn": ["0022-0965", "1096-0457"],
    "aliases": ["J Exp Child Psychol"],
    "publisher": "Elsevier",
    "field": "experimental-child-psychology",
    "priority": "core"
  },
  {
    "id": "infancy",
    "name": "Infancy",
    "issn": ["1532-7078"],
    "aliases": ["Infancy"],
    "publisher": "ICIS / Wiley",
    "field": "infant-development",
    "priority": "core"
  },
  {
    "id": "journal-of-child-language",
    "name": "Journal of Child Language",
    "issn": ["0305-0009"],
    "aliases": ["J Child Lang"],
    "publisher": "Cambridge University Press",
    "field": "language-development",
    "priority": "flagship"
  },
  {
    "id": "language-learning-development",
    "name": "Language Learning and Development",
    "issn": ["1547-5441", "1547-3341"],
    "aliases": ["Lang Learn Dev"],
    "publisher": "Taylor & Francis",
    "field": "language-development",
    "priority": "core"
  },
  {
    "id": "journal-of-memory-and-language",
    "name": "Journal of Memory and Language",
    "issn": ["0749-596X", "1096-0821"],
    "aliases": ["J Mem Lang"],
    "publisher": "Elsevier",
    "field": "psycholinguistics",
    "priority": "flagship"
  },
  {
    "id": "applied-psycholinguistics",
    "name": "Applied Psycholinguistics",
    "issn": ["0142-7164", "1469-1817"],
    "aliases": ["Appl Psycholinguist"],
    "publisher": "Cambridge University Press",
    "field": "applied-psycholinguistics",
    "priority": "core"
  },
  {
    "id": "first-language",
    "name": "First Language",
    "issn": ["0142-7237"],
    "aliases": ["First Lang"],
    "publisher": "SAGE",
    "field": "language-development",
    "priority": "core"
  }
]
